xtsqlorm/__init__.py
xtsqlorm/async_engine.py
xtsqlorm/async_repository.py
xtsqlorm/async_session.py
xtsqlorm/base.py
xtsqlorm/cfg.py
xtsqlorm/engine.py
xtsqlorm/factory.py
xtsqlorm/mixins.py
xtsqlorm/operations.py
xtsqlorm/protocols.py
xtsqlorm/repository.py
xtsqlorm/session.py
xtsqlorm/sql_builder.py
xtsqlorm/table_utils.py
xtsqlorm/types.py
xtsqlorm/uow.py
xtsqlorm/validators.py
xtsqlorm-0.1.0.dist-info/licenses/LICENSE
xtsqlorm-0.1.0.dist-info/METADATA
xtsqlorm-0.1.0.dist-info/WHEEL
xtsqlorm-0.1.0.dist-info/top_level.txt
xtsqlorm-0.1.0.dist-info/RECORD
