Metadata-Version: 2.4
Name: xtsqlorm
Version: 0.1.0
Summary: Add your description here
Project-URL: homepage, https://github.com/sandorn/xtsqlorm
Project-URL: repository, https://github.com/sandorn/xtsqlorm
Project-URL: documentation, https://github.com/sandorn/xtsqlorm/wiki
Classifier: Development Status :: 4 - Beta
Classifier: Intended Audience :: Developers
Classifier: License :: OSI Approved :: MIT License
Classifier: Programming Language :: Python :: 3.13
Classifier: Topic :: Software Development :: Libraries :: Python Modules
Classifier: Topic :: Utilities
Requires-Python: >=3.14
License-File: LICENSE
Requires-Dist: aiomysql>=0.3.2
Requires-Dist: mysql-connector-python>=9.5.0
Requires-Dist: pandas>=2.3.3
Requires-Dist: pydantic[all,email]>=2.12.3
Requires-Dist: pymysql>=1.1.2
Requires-Dist: sqlacodegen>=3.0.0
Requires-Dist: sqlalchemy>=2.0.44
Requires-Dist: xtlog>=0.1.9
Requires-Dist: xtwraps>=0.2.1
Provides-Extra: test
Dynamic: license-file
